pypaste/__init__.py
pypaste/pypaste.py
pypaste-0.1.0.dist-info/AUTHORS.rst
pypaste-0.1.0.dist-info/LICENSE
pypaste-0.1.0.dist-info/METADATA
pypaste-0.1.0.dist-info/WHEEL
pypaste-0.1.0.dist-info/top_level.txt
pypaste-0.1.0.dist-info/RECORD
