Metadata-Version: 2.1
Name: pypaste
Version: 0.1.0
Summary: Cross-platform Python clipboard library
Home-page: https://github.com/joelfrederico/pypaste
Author: Joel Travis Frederico
Author-email: joelfrederico@gmail.com
License: MIT license
Keywords: pypaste
Platform: UNKNOWN
Classifier: Development Status :: 2 - Pre-Alpha
Classifier: Intended Audience :: Developers
Classifier: License :: OSI Approved :: MIT License
Classifier: Natural Language :: English
Classifier: Programming Language :: Python :: 2
Classifier: Programming Language :: Python :: 2.7
Classifier: Programming Language :: Python :: 3
Classifier: Programming Language :: Python :: 3.4
Classifier: Programming Language :: Python :: 3.5
Classifier: Programming Language :: Python :: 3.6
Classifier: Programming Language :: Python :: 3.7
